objects_api_client_django-0.5.0.dist-info/licenses/LICENSE
objectsapiclient/__init__.py
objectsapiclient/admin.py
objectsapiclient/apps.py
objectsapiclient/dataclasses.py
objectsapiclient/exceptions.py
objectsapiclient/models.py
objectsapiclient/services.py
objectsapiclient/utils.py
objectsapiclient/migrations/0001_initial.py
objectsapiclient/migrations/0002_auto_20230917_1644.py
objectsapiclient/migrations/0003_rename_config_model_fields.py
objectsapiclient/migrations/0004_alter_objectsclientconfiguration_options_and_more.py
objectsapiclient/migrations/0005_rename_objectsclientconfiguration.py
objectsapiclient/migrations/__init__.py
objects_api_client_django-0.5.0.dist-info/METADATA
objects_api_client_django-0.5.0.dist-info/WHEEL
objects_api_client_django-0.5.0.dist-info/top_level.txt
objects_api_client_django-0.5.0.dist-info/RECORD
