Metadata-Version: 2.4
Name: objects-api-client-django
Version: 0.5.0
Summary: Easily integrate Objects API in your Django application.
Author-email: Maykin <support@maykinmedia.nl>
License: MIT
Project-URL: Homepage, https://github.com/maykinmedia/objects-api-client-django
Keywords: Objects API,Client,Django
Classifier: Development Status :: 3 - Alpha
Classifier: Framework :: Django
Classifier: Framework :: Django :: 4.2
Classifier: Intended Audience :: Developers
Classifier: Operating System :: Unix
Classifier: Operating System :: MacOS
Classifier: Operating System :: Microsoft :: Windows
Classifier: Programming Language :: Python :: 3.11
Classifier: Programming Language :: Python :: 3.12
Classifier: Programming Language :: Python :: 3.13
Classifier: Topic :: Software Development :: Libraries :: Python Modules
Requires-Python: >=3.11
License-File: LICENSE
Requires-Dist: django>=4.2
Requires-Dist: django-solo
Requires-Dist: ape_pie
Requires-Dist: pydantic>=2.0
Requires-Dist: requests
Requires-Dist: zgw_consumers
Provides-Extra: tests
Requires-Dist: requests-mock; extra == "tests"
Requires-Dist: pytest; extra == "tests"
Requires-Dist: pytest-django; extra == "tests"
Requires-Dist: tox; extra == "tests"
Requires-Dist: ruff; extra == "tests"
Provides-Extra: coverage
Requires-Dist: pytest-cov; extra == "coverage"
Provides-Extra: release
Requires-Dist: twine; extra == "release"
Dynamic: license-file
